django_vtasks/__init__.py
django_vtasks/admin.py
django_vtasks/admin_valkey.py
django_vtasks/apps.py
django_vtasks/asgi.py
django_vtasks/conf.py
django_vtasks/empty_urls.py
django_vtasks/metrics.py
django_vtasks/scheduler.py
django_vtasks/serialization.py
django_vtasks/signals.py
django_vtasks/tasks.py
django_vtasks/utils.py
django_vtasks/worker.py
django_vtasks/backends/__init__.py
django_vtasks/backends/base.py
django_vtasks/backends/db.py
django_vtasks/backends/immediate.py
django_vtasks/backends/valkey.py
django_vtasks/db/__init__.py
django_vtasks/db/admin.py
django_vtasks/db/apps.py
django_vtasks/db/models.py
django_vtasks/db/migrations/0001_initial.py
django_vtasks/db/migrations/0002_remove_queuedtask_db_queuedta_queue_2cd03b_idx_and_more.py
django_vtasks/db/migrations/__init__.py
django_vtasks/management/__init__.py
django_vtasks/management/commands/__init__.py
django_vtasks/management/commands/benchmark_vtasks.py
django_vtasks/management/commands/clear_queue.py
django_vtasks/management/commands/runworker.py
django_vtasks/templates/admin/django_vtasks/valkeytask/valkey_change_list.html
django_vtasks/templatetags/__init__.py
django_vtasks/templatetags/valkey_admin_filters.py
django_vtasks-1.0.1.dist-info/METADATA
django_vtasks-1.0.1.dist-info/WHEEL
django_vtasks-1.0.1.dist-info/licenses/LICENSE
django_vtasks-1.0.1.dist-info/RECORD
