Metadata-Version: 2.4
Name: django-vtasks
Version: 1.0.1
Summary: A very fast valkey/postgres django tasks backend.
Project-URL: Source, https://gitlab.com/glitchtip/django-vtasks
Project-URL: Tracker, https://gitlab.com/glitchtip/django-vtasks/-/issues
License-Expression: MIT
License-File: LICENSE
Keywords: background,django,postgres,tasks,valkey
Classifier: Framework :: Django
Classifier: License :: OSI Approved :: MIT License
Classifier: Operating System :: OS Independent
Classifier: Programming Language :: Python :: 3
Classifier: Programming Language :: Python :: 3.12
Classifier: Programming Language :: Python :: 3.13
Classifier: Programming Language :: Python :: 3.14
Requires-Python: >=3.12
Requires-Dist: croniter>=2.0.4
Requires-Dist: django>=6.0
Requires-Dist: orjson>=3.11.4
Requires-Dist: zstandard>=0.15.0; python_version < '3.14'
Provides-Extra: metrics
Requires-Dist: prometheus-client>=0.17.0; extra == 'metrics'
Provides-Extra: valkey
Requires-Dist: valkey[libvalkey]>=6.1.1; extra == 'valkey'
